dds238/__init__.py
dds238/dds238.py
python_dds238-0.0.5.dist-info/METADATA
python_dds238-0.0.5.dist-info/WHEEL
python_dds238-0.0.5.dist-info/top_level.txt
python_dds238-0.0.5.dist-info/RECORD
