Metadata-Version: 2.1
Name: python-dds238
Version: 0.0.5
Summary: Reads DDS238 meters via modbus
Home-page: https://github.com/Frankkkkk/python-dds238
Author: Frank Villaro-Dixon
Author-email: frank@villaro-dixon.eu
License: MIT
Keywords: dds238 power meter modbus
Platform: UNKNOWN
Classifier: Development Status :: 3 - Alpha
Classifier: Topic :: Utilities
Classifier: License :: OSI Approved :: MIT License
Requires-Dist: minimalmodbus
